openbb_akshare/__init__.py
openbb_akshare/models/__init__.py
openbb_akshare/models/available_indices.py
openbb_akshare/models/balance_sheet.py
openbb_akshare/models/business_analysis.py
openbb_akshare/models/cash_flow.py
openbb_akshare/models/company_news.py
openbb_akshare/models/currency_historical.py
openbb_akshare/models/currency_snapshots.py
openbb_akshare/models/equity_historical.py
openbb_akshare/models/equity_ownership.py
openbb_akshare/models/equity_profile.py
openbb_akshare/models/equity_quote.py
openbb_akshare/models/equity_screener.py
openbb_akshare/models/equity_search.py
openbb_akshare/models/etf_holdings.py
openbb_akshare/models/etf_search.py
openbb_akshare/models/fund_holdings.py
openbb_akshare/models/historical_dividends.py
openbb_akshare/models/income_statement.py
openbb_akshare/models/key_metrics.py
openbb_akshare/models/price_performance.py
openbb_akshare/openbb.py
openbb_akshare/router.py
openbb_akshare/standard_models/__init__.py
openbb_akshare/standard_models/business_analysis.py
openbb_akshare/standard_models/fund_holdings.py
openbb_akshare/utils/__init__.py
openbb_akshare/utils/ak_balance_sheet.py
openbb_akshare/utils/ak_cash_flow.py
openbb_akshare/utils/ak_compare_company_facts.py
openbb_akshare/utils/ak_equity_ownership.py
openbb_akshare/utils/ak_equity_search.py
openbb_akshare/utils/ak_income_statement.py
openbb_akshare/utils/ak_key_metrics.py
openbb_akshare/utils/fetch_equity_info.py
openbb_akshare/utils/fetch_quote.py
openbb_akshare/utils/futures.csv
openbb_akshare/utils/helpers.py
openbb_akshare/utils/references.py
openbb_akshare-1.0.8.dist-info/entry_points.txt
openbb_akshare-1.0.8.dist-info/METADATA
openbb_akshare-1.0.8.dist-info/WHEEL
openbb_akshare-1.0.8.dist-info/RECORD
