Metadata-Version: 2.3
Name: openbb-akshare
Version: 1.0.8
Summary: AKShare extension for OpenBB
License: AGPL-3.0-only
Author: Roger Ye
Author-email: shugaoye@yahoo.com
Requires-Python: >=3.11,<3.13
Classifier: License :: OSI Approved :: GNU Affero General Public License v3
Classifier: Programming Language :: Python :: 3
Classifier: Programming Language :: Python :: 3.11
Classifier: Programming Language :: Python :: 3.12
Requires-Dist: akshare (==1.17.91)
Requires-Dist: ipywidgets (>=8.1.7,<9.0.0)
Requires-Dist: mysharelib (>=1.0.4,<2.0.0)
Requires-Dist: openbb (==4.5.0)
Requires-Dist: openbb-core (>=1.5.6,<2.0.0)
